CHANGES.txt
LICENSE.txt
MANIFEST.in
setup.py
docs/source/api.rst
docs/source/index.rst
python_restorable_collections.egg-info/PKG-INFO
python_restorable_collections.egg-info/SOURCES.txt
python_restorable_collections.egg-info/dependency_links.txt
python_restorable_collections.egg-info/top_level.txt
python_restorable_collections.egg-info/zip-safe
source/restorable_collections/__init__.py