Metadata-Version: 1.1
Name: python-restorable-collections
Version: 1.0.0
Summary: Pickleable wrappers for Python collections with non-built-in type keys and cycles or self-references.
Home-page: http://www.petrounias.org/software/python-restorable-collections/
Author: Alexis Petrounias <www.petrounias.org>
Author-email: UNKNOWN
License: BSD
Download-URL: https://github.com/petrounias/python-restorable-collections/archive/master.zip
Keywords: collections,pickle,pickling,unpickling,cPickle,cycles,self-references
Platform: UNKNOWN
Classifier: Development Status :: 5 - Production/Stable
Classifier: Intended Audience :: Developers
Classifier: License :: OSI Approved :: BSD License
Classifier: Operating System :: OS Independent
Classifier: Programming Language :: Python
Classifier: Topic :: Software Development :: Libraries :: Python Modules
